README.md
setup.cfg
setup.py
tvm/__init__.py
tvm_ffi.egg-info/PKG-INFO
tvm_ffi.egg-info/SOURCES.txt
tvm_ffi.egg-info/dependency_links.txt
tvm_ffi.egg-info/top_level.txt