Metadata-Version: 2.1
Name: tvm-ffi
Version: 0.1
Summary: Machine learning for systems
Home-page: https://github.com/apache/tvm
Author: 
Author-email: tianqi.tchen@gmail.com
License: Apache-2.0
Classifier: Development Status :: 3 - Alpha
Classifier: Intended Audience :: Developers
Classifier: Topic :: Software Development :: Build Tools
Classifier: License :: OSI Approved :: Apache Software License
Classifier: Programming Language :: Python :: 3
